upnpme/UPnPMe.py
upnpme/__init__.py
UPnPMe-0.1.dist-info/LICENSE
UPnPMe-0.1.dist-info/METADATA
UPnPMe-0.1.dist-info/WHEEL
UPnPMe-0.1.dist-info/top_level.txt
UPnPMe-0.1.dist-info/RECORD
